caffee.py
caffee-2.9.2.dist-info/METADATA
caffee-2.9.2.dist-info/WHEEL
caffee-2.9.2.dist-info/entry_points.txt
caffee-2.9.2.dist-info/licenses/LICENSE
caffee-2.9.2.dist-info/RECORD
