Metadata-Version: 2.4
Name: caffee
Version: 2.9.2
Summary: A simple CUI editor for Caffee.
Project-URL: Homepage, https://github.com/iamthe000/CAFFEE_Editor
Author-email: iamthe000 <your_email@example.com>
License: GPL-3.0-or-later
License-File: LICENSE
Keywords: cli,cui,editor,terminal
Classifier: Development Status :: 5 - Production/Stable
Classifier: Environment :: Console
Classifier: License :: OSI Approved :: GNU General Public License v3 or later (GPLv3+)
Classifier: Operating System :: OS Independent
Classifier: Programming Language :: Python :: 3
Classifier: Topic :: Text Editors
Requires-Python: >=3.8
